pyredox/__init__.py
pyredox/abstract_base.py
pyredox/claim/__init__.py
pyredox/claim/payment.py
pyredox/claim/paymentbatch.py
pyredox/claim/submission.py
pyredox/claim/submissionbatch.py
pyredox/clinicaldecisions/__init__.py
pyredox/clinicaldecisions/request.py
pyredox/clinicaldecisions/response.py
pyredox/clinicalsummary/__init__.py
pyredox/clinicalsummary/documentget.py
pyredox/clinicalsummary/documentgetresponse.py
pyredox/clinicalsummary/documentquery.py
pyredox/clinicalsummary/documentqueryresponse.py
pyredox/clinicalsummary/patientpush.py
pyredox/clinicalsummary/patientquery.py
pyredox/clinicalsummary/patientqueryresponse.py
pyredox/clinicalsummary/visitpush.py
pyredox/clinicalsummary/visitquery.py
pyredox/clinicalsummary/visitqueryresponse.py
pyredox/device/__init__.py
pyredox/device/new.py
pyredox/enrichment/__init__.py
pyredox/enrichment/naturallanguageprocessingquery.py
pyredox/enrichment/naturallanguageprocessingqueryresponse.py
pyredox/enrichment/normalizationquery.py
pyredox/enrichment/normalizationqueryresponse.py
pyredox/factory.py
pyredox/field_types.py
pyredox/financial/__init__.py
pyredox/financial/accountupdate.py
pyredox/financial/transaction.py
pyredox/flowsheet/__init__.py
pyredox/flowsheet/new.py
pyredox/generic/Claim.py
pyredox/generic/ClinicalDecisions.py
pyredox/generic/ClinicalSummary.py
pyredox/generic/Device.py
pyredox/generic/Enrichment.py
pyredox/generic/Financial.py
pyredox/generic/Flowsheet.py
pyredox/generic/Inventory.py
pyredox/generic/Media.py
pyredox/generic/Medications.py
pyredox/generic/Notes.py
pyredox/generic/Order.py
pyredox/generic/Organization.py
pyredox/generic/PatientAdmin.py
pyredox/generic/PatientEducation.py
pyredox/generic/PatientSearch.py
pyredox/generic/Provider.py
pyredox/generic/Referral.py
pyredox/generic/Research.py
pyredox/generic/Results.py
pyredox/generic/SSO.py
pyredox/generic/Scheduling.py
pyredox/generic/SurgicalScheduling.py
pyredox/generic/Vaccination.py
pyredox/generic/__init__.py
pyredox-1.0.4.dist-info/LICENSE
pyredox-1.0.4.dist-info/METADATA
pyredox-1.0.4.dist-info/WHEEL
pyredox-1.0.4.dist-info/RECORD
